/*   1:    */ package org.apache.bcel;
/*   2:    */ 
/*   3:    */ public abstract interface Constants
/*   4:    */ {
/*   5:    */   public static final short MAJOR_1_1 = 45;
/*   6:    */   public static final short MINOR_1_1 = 3;
/*   7:    */   public static final short MAJOR_1_2 = 46;
/*   8:    */   public static final short MINOR_1_2 = 0;
/*   9:    */   public static final short MAJOR_1_3 = 47;
/*  10:    */   public static final short MINOR_1_3 = 0;
/*  11:    */   public static final short MAJOR = 45;
/*  12:    */   public static final short MINOR = 3;
/*  13:    */   public static final int MAX_SHORT = 65535;
/*  14:    */   public static final int MAX_BYTE = 255;
/*  15:    */   public static final short ACC_PUBLIC = 1;
/*  16:    */   public static final short ACC_PRIVATE = 2;
/*  17:    */   public static final short ACC_PROTECTED = 4;
/*  18:    */   public static final short ACC_STATIC = 8;
/*  19:    */   public static final short ACC_FINAL = 16;
/*  20:    */   public static final short ACC_SYNCHRONIZED = 32;
/*  21:    */   public static final short ACC_VOLATILE = 64;
/*  22:    */   public static final short ACC_TRANSIENT = 128;
/*  23:    */   public static final short ACC_NATIVE = 256;
/*  24:    */   public static final short ACC_INTERFACE = 512;
/*  25:    */   public static final short ACC_ABSTRACT = 1024;
/*  26:    */   public static final short ACC_STRICT = 2048;
/*  27:    */   public static final short ACC_SUPER = 32;
/*  28:    */   public static final short MAX_ACC_FLAG = 1024;
/*  29:105 */   public static final String[] ACCESS_NAMES = { "public", "private", "protected", "static", "final", "synchronized", "volatile", "transient", "native", "interface", "abstract" };
/*  30:    */   public static final byte CONSTANT_Utf8 = 1;
/*  31:    */   public static final byte CONSTANT_Integer = 3;
/*  32:    */   public static final byte CONSTANT_Float = 4;
/*  33:    */   public static final byte CONSTANT_Long = 5;
/*  34:    */   public static final byte CONSTANT_Double = 6;
/*  35:    */   public static final byte CONSTANT_Class = 7;
/*  36:    */   public static final byte CONSTANT_Fieldref = 9;
/*  37:    */   public static final byte CONSTANT_String = 8;
/*  38:    */   public static final byte CONSTANT_Methodref = 10;
/*  39:    */   public static final byte CONSTANT_InterfaceMethodref = 11;
/*  40:    */   public static final byte CONSTANT_NameAndType = 12;
/*  41:124 */   public static final String[] CONSTANT_NAMES = { "", "CONSTANT_Utf8", "", "CONSTANT_Integer", "CONSTANT_Float", "CONSTANT_Long", "CONSTANT_Double", "CONSTANT_Class", "CONSTANT_String", "CONSTANT_Fieldref", "CONSTANT_Methodref", "CONSTANT_InterfaceMethodref", "CONSTANT_NameAndType" };
/*  42:    */   public static final String STATIC_INITIALIZER_NAME = "<clinit>";
/*  43:    */   public static final String CONSTRUCTOR_NAME = "<init>";
/*  44:143 */   public static final String[] INTERFACES_IMPLEMENTED_BY_ARRAYS = { "java.lang.Cloneable", "java.io.Serializable" };
/*  45:    */   public static final int MAX_CP_ENTRIES = 65535;
/*  46:    */   public static final int MAX_CODE_SIZE = 65536;
/*  47:    */   public static final short NOP = 0;
/*  48:    */   public static final short ACONST_NULL = 1;
/*  49:    */   public static final short ICONST_M1 = 2;
/*  50:    */   public static final short ICONST_0 = 3;
/*  51:    */   public static final short ICONST_1 = 4;
/*  52:    */   public static final short ICONST_2 = 5;
/*  53:    */   public static final short ICONST_3 = 6;
/*  54:    */   public static final short ICONST_4 = 7;
/*  55:    */   public static final short ICONST_5 = 8;
/*  56:    */   public static final short LCONST_0 = 9;
/*  57:    */   public static final short LCONST_1 = 10;
/*  58:    */   public static final short FCONST_0 = 11;
/*  59:    */   public static final short FCONST_1 = 12;
/*  60:    */   public static final short FCONST_2 = 13;
/*  61:    */   public static final short DCONST_0 = 14;
/*  62:    */   public static final short DCONST_1 = 15;
/*  63:    */   public static final short BIPUSH = 16;
/*  64:    */   public static final short SIPUSH = 17;
/*  65:    */   public static final short LDC = 18;
/*  66:    */   public static final short LDC_W = 19;
/*  67:    */   public static final short LDC2_W = 20;
/*  68:    */   public static final short ILOAD = 21;
/*  69:    */   public static final short LLOAD = 22;
/*  70:    */   public static final short FLOAD = 23;
/*  71:    */   public static final short DLOAD = 24;
/*  72:    */   public static final short ALOAD = 25;
/*  73:    */   public static final short ILOAD_0 = 26;
/*  74:    */   public static final short ILOAD_1 = 27;
/*  75:    */   public static final short ILOAD_2 = 28;
/*  76:    */   public static final short ILOAD_3 = 29;
/*  77:    */   public static final short LLOAD_0 = 30;
/*  78:    */   public static final short LLOAD_1 = 31;
/*  79:    */   public static final short LLOAD_2 = 32;
/*  80:    */   public static final short LLOAD_3 = 33;
/*  81:    */   public static final short FLOAD_0 = 34;
/*  82:    */   public static final short FLOAD_1 = 35;
/*  83:    */   public static final short FLOAD_2 = 36;
/*  84:    */   public static final short FLOAD_3 = 37;
/*  85:    */   public static final short DLOAD_0 = 38;
/*  86:    */   public static final short DLOAD_1 = 39;
/*  87:    */   public static final short DLOAD_2 = 40;
/*  88:    */   public static final short DLOAD_3 = 41;
/*  89:    */   public static final short ALOAD_0 = 42;
/*  90:    */   public static final short ALOAD_1 = 43;
/*  91:    */   public static final short ALOAD_2 = 44;
/*  92:    */   public static final short ALOAD_3 = 45;
/*  93:    */   public static final short IALOAD = 46;
/*  94:    */   public static final short LALOAD = 47;
/*  95:    */   public static final short FALOAD = 48;
/*  96:    */   public static final short DALOAD = 49;
/*  97:    */   public static final short AALOAD = 50;
/*  98:    */   public static final short BALOAD = 51;
/*  99:    */   public static final short CALOAD = 52;
/* 100:    */   public static final short SALOAD = 53;
/* 101:    */   public static final short ISTORE = 54;
/* 102:    */   public static final short LSTORE = 55;
/* 103:    */   public static final short FSTORE = 56;
/* 104:    */   public static final short DSTORE = 57;
/* 105:    */   public static final short ASTORE = 58;
/* 106:    */   public static final short ISTORE_0 = 59;
/* 107:    */   public static final short ISTORE_1 = 60;
/* 108:    */   public static final short ISTORE_2 = 61;
/* 109:    */   public static final short ISTORE_3 = 62;
/* 110:    */   public static final short LSTORE_0 = 63;
/* 111:    */   public static final short LSTORE_1 = 64;
/* 112:    */   public static final short LSTORE_2 = 65;
/* 113:    */   public static final short LSTORE_3 = 66;
/* 114:    */   public static final short FSTORE_0 = 67;
/* 115:    */   public static final short FSTORE_1 = 68;
/* 116:    */   public static final short FSTORE_2 = 69;
/* 117:    */   public static final short FSTORE_3 = 70;
/* 118:    */   public static final short DSTORE_0 = 71;
/* 119:    */   public static final short DSTORE_1 = 72;
/* 120:    */   public static final short DSTORE_2 = 73;
/* 121:    */   public static final short DSTORE_3 = 74;
/* 122:    */   public static final short ASTORE_0 = 75;
/* 123:    */   public static final short ASTORE_1 = 76;
/* 124:    */   public static final short ASTORE_2 = 77;
/* 125:    */   public static final short ASTORE_3 = 78;
/* 126:    */   public static final short IASTORE = 79;
/* 127:    */   public static final short LASTORE = 80;
/* 128:    */   public static final short FASTORE = 81;
/* 129:    */   public static final short DASTORE = 82;
/* 130:    */   public static final short AASTORE = 83;
/* 131:    */   public static final short BASTORE = 84;
/* 132:    */   public static final short CASTORE = 85;
/* 133:    */   public static final short SASTORE = 86;
/* 134:    */   public static final short POP = 87;
/* 135:    */   public static final short POP2 = 88;
/* 136:    */   public static final short DUP = 89;
/* 137:    */   public static final short DUP_X1 = 90;
/* 138:    */   public static final short DUP_X2 = 91;
/* 139:    */   public static final short DUP2 = 92;
/* 140:    */   public static final short DUP2_X1 = 93;
/* 141:    */   public static final short DUP2_X2 = 94;
/* 142:    */   public static final short SWAP = 95;
/* 143:    */   public static final short IADD = 96;
/* 144:    */   public static final short LADD = 97;
/* 145:    */   public static final short FADD = 98;
/* 146:    */   public static final short DADD = 99;
/* 147:    */   public static final short ISUB = 100;
/* 148:    */   public static final short LSUB = 101;
/* 149:    */   public static final short FSUB = 102;
/* 150:    */   public static final short DSUB = 103;
/* 151:    */   public static final short IMUL = 104;
/* 152:    */   public static final short LMUL = 105;
/* 153:    */   public static final short FMUL = 106;
/* 154:    */   public static final short DMUL = 107;
/* 155:    */   public static final short IDIV = 108;
/* 156:    */   public static final short LDIV = 109;
/* 157:    */   public static final short FDIV = 110;
/* 158:    */   public static final short DDIV = 111;
/* 159:    */   public static final short IREM = 112;
/* 160:    */   public static final short LREM = 113;
/* 161:    */   public static final short FREM = 114;
/* 162:    */   public static final short DREM = 115;
/* 163:    */   public static final short INEG = 116;
/* 164:    */   public static final short LNEG = 117;
/* 165:    */   public static final short FNEG = 118;
/* 166:    */   public static final short DNEG = 119;
/* 167:    */   public static final short ISHL = 120;
/* 168:    */   public static final short LSHL = 121;
/* 169:    */   public static final short ISHR = 122;
/* 170:    */   public static final short LSHR = 123;
/* 171:    */   public static final short IUSHR = 124;
/* 172:    */   public static final short LUSHR = 125;
/* 173:    */   public static final short IAND = 126;
/* 174:    */   public static final short LAND = 127;
/* 175:    */   public static final short IOR = 128;
/* 176:    */   public static final short LOR = 129;
/* 177:    */   public static final short IXOR = 130;
/* 178:    */   public static final short LXOR = 131;
/* 179:    */   public static final short IINC = 132;
/* 180:    */   public static final short I2L = 133;
/* 181:    */   public static final short I2F = 134;
/* 182:    */   public static final short I2D = 135;
/* 183:    */   public static final short L2I = 136;
/* 184:    */   public static final short L2F = 137;
/* 185:    */   public static final short L2D = 138;
/* 186:    */   public static final short F2I = 139;
/* 187:    */   public static final short F2L = 140;
/* 188:    */   public static final short F2D = 141;
/* 189:    */   public static final short D2I = 142;
/* 190:    */   public static final short D2L = 143;
/* 191:    */   public static final short D2F = 144;
/* 192:    */   public static final short I2B = 145;
/* 193:    */   public static final short INT2BYTE = 145;
/* 194:    */   public static final short I2C = 146;
/* 195:    */   public static final short INT2CHAR = 146;
/* 196:    */   public static final short I2S = 147;
/* 197:    */   public static final short INT2SHORT = 147;
/* 198:    */   public static final short LCMP = 148;
/* 199:    */   public static final short FCMPL = 149;
/* 200:    */   public static final short FCMPG = 150;
/* 201:    */   public static final short DCMPL = 151;
/* 202:    */   public static final short DCMPG = 152;
/* 203:    */   public static final short IFEQ = 153;
/* 204:    */   public static final short IFNE = 154;
/* 205:    */   public static final short IFLT = 155;
/* 206:    */   public static final short IFGE = 156;
/* 207:    */   public static final short IFGT = 157;
/* 208:    */   public static final short IFLE = 158;
/* 209:    */   public static final short IF_ICMPEQ = 159;
/* 210:    */   public static final short IF_ICMPNE = 160;
/* 211:    */   public static final short IF_ICMPLT = 161;
/* 212:    */   public static final short IF_ICMPGE = 162;
/* 213:    */   public static final short IF_ICMPGT = 163;
/* 214:    */   public static final short IF_ICMPLE = 164;
/* 215:    */   public static final short IF_ACMPEQ = 165;
/* 216:    */   public static final short IF_ACMPNE = 166;
/* 217:    */   public static final short GOTO = 167;
/* 218:    */   public static final short JSR = 168;
/* 219:    */   public static final short RET = 169;
/* 220:    */   public static final short TABLESWITCH = 170;
/* 221:    */   public static final short LOOKUPSWITCH = 171;
/* 222:    */   public static final short IRETURN = 172;
/* 223:    */   public static final short LRETURN = 173;
/* 224:    */   public static final short FRETURN = 174;
/* 225:    */   public static final short DRETURN = 175;
/* 226:    */   public static final short ARETURN = 176;
/* 227:    */   public static final short RETURN = 177;
/* 228:    */   public static final short GETSTATIC = 178;
/* 229:    */   public static final short PUTSTATIC = 179;
/* 230:    */   public static final short GETFIELD = 180;
/* 231:    */   public static final short PUTFIELD = 181;
/* 232:    */   public static final short INVOKEVIRTUAL = 182;
/* 233:    */   public static final short INVOKESPECIAL = 183;
/* 234:    */   public static final short INVOKENONVIRTUAL = 183;
/* 235:    */   public static final short INVOKESTATIC = 184;
/* 236:    */   public static final short INVOKEINTERFACE = 185;
/* 237:    */   public static final short NEW = 187;
/* 238:    */   public static final short NEWARRAY = 188;
/* 239:    */   public static final short ANEWARRAY = 189;
/* 240:    */   public static final short ARRAYLENGTH = 190;
/* 241:    */   public static final short ATHROW = 191;
/* 242:    */   public static final short CHECKCAST = 192;
/* 243:    */   public static final short INSTANCEOF = 193;
/* 244:    */   public static final short MONITORENTER = 194;
/* 245:    */   public static final short MONITOREXIT = 195;
/* 246:    */   public static final short WIDE = 196;
/* 247:    */   public static final short MULTIANEWARRAY = 197;
/* 248:    */   public static final short IFNULL = 198;
/* 249:    */   public static final short IFNONNULL = 199;
/* 250:    */   public static final short GOTO_W = 200;
/* 251:    */   public static final short JSR_W = 201;
/* 252:    */   public static final short BREAKPOINT = 202;
/* 253:    */   public static final short LDC_QUICK = 203;
/* 254:    */   public static final short LDC_W_QUICK = 204;
/* 255:    */   public static final short LDC2_W_QUICK = 205;
/* 256:    */   public static final short GETFIELD_QUICK = 206;
/* 257:    */   public static final short PUTFIELD_QUICK = 207;
/* 258:    */   public static final short GETFIELD2_QUICK = 208;
/* 259:    */   public static final short PUTFIELD2_QUICK = 209;
/* 260:    */   public static final short GETSTATIC_QUICK = 210;
/* 261:    */   public static final short PUTSTATIC_QUICK = 211;
/* 262:    */   public static final short GETSTATIC2_QUICK = 212;
/* 263:    */   public static final short PUTSTATIC2_QUICK = 213;
/* 264:    */   public static final short INVOKEVIRTUAL_QUICK = 214;
/* 265:    */   public static final short INVOKENONVIRTUAL_QUICK = 215;
/* 266:    */   public static final short INVOKESUPER_QUICK = 216;
/* 267:    */   public static final short INVOKESTATIC_QUICK = 217;
/* 268:    */   public static final short INVOKEINTERFACE_QUICK = 218;
/* 269:    */   public static final short INVOKEVIRTUALOBJECT_QUICK = 219;
/* 270:    */   public static final short NEW_QUICK = 221;
/* 271:    */   public static final short ANEWARRAY_QUICK = 222;
/* 272:    */   public static final short MULTIANEWARRAY_QUICK = 223;
/* 273:    */   public static final short CHECKCAST_QUICK = 224;
/* 274:    */   public static final short INSTANCEOF_QUICK = 225;
/* 275:    */   public static final short INVOKEVIRTUAL_QUICK_W = 226;
/* 276:    */   public static final short GETFIELD_QUICK_W = 227;
/* 277:    */   public static final short PUTFIELD_QUICK_W = 228;
/* 278:    */   public static final short IMPDEP1 = 254;
/* 279:    */   public static final short IMPDEP2 = 255;
/* 280:    */   public static final short PUSH = 4711;
/* 281:    */   public static final short SWITCH = 4712;
/* 282:    */   public static final short UNDEFINED = -1;
/* 283:    */   public static final short UNPREDICTABLE = -2;
/* 284:    */   public static final short RESERVED = -3;
/* 285:    */   public static final String ILLEGAL_OPCODE = "<illegal opcode>";
/* 286:    */   public static final String ILLEGAL_TYPE = "<illegal type>";
/* 287:    */   public static final byte T_BOOLEAN = 4;
/* 288:    */   public static final byte T_CHAR = 5;
/* 289:    */   public static final byte T_FLOAT = 6;
/* 290:    */   public static final byte T_DOUBLE = 7;
/* 291:    */   public static final byte T_BYTE = 8;
/* 292:    */   public static final byte T_SHORT = 9;
/* 293:    */   public static final byte T_INT = 10;
/* 294:    */   public static final byte T_LONG = 11;
/* 295:    */   public static final byte T_VOID = 12;
/* 296:    */   public static final byte T_ARRAY = 13;
/* 297:    */   public static final byte T_OBJECT = 14;
/* 298:    */   public static final byte T_REFERENCE = 14;
/* 299:    */   public static final byte T_UNKNOWN = 15;
/* 300:    */   public static final byte T_ADDRESS = 16;
/* 301:423 */   public static final String[] TYPE_NAMES = { "<illegal type>", "<illegal type>", "<illegal type>", "<illegal type>", "boolean", "char", "float", "double", "byte", "short", "int", "long", "void", "array", "object", "unknown" };
/* 302:429 */   public static final String[] SHORT_TYPE_NAMES = { "<illegal type>", "<illegal type>", "<illegal type>", "<illegal type>", "Z", "C", "F", "D", "B", "S", "I", "J", "V", "<illegal type>", "<illegal type>", "<illegal type>" };
/* 303:439 */   public static final short[] NO_OF_OPERANDS = { 0, 0, 0, 0, 0, 0, 0, 0, 0, 0, 0, 0, 0, 0, 0, 0, 1, 2, 1, 2, 2, 1, 1, 1, 1, 1, 0, 0, 0, 0, 0, 0, 0, 0, 0, 0, 0, 0, 0, 0, 0, 0, 0, 0, 0, 0, 0, 0, 0, 0, 0, 0, 0, 0, 1, 1, 1, 1, 1, 0, 0, 0, 0, 0, 0, 0, 0, 0, 0, 0, 0, 0, 0, 0, 0, 0, 0, 0, 0, 0, 0, 0, 0, 0, 0, 0, 0, 0, 0, 0, 0, 0, 0, 0, 0, 0, 0, 0, 0, 0, 0, 0, 0, 0, 0, 0, 0, 0, 0, 0, 0, 0, 0, 0, 0, 0, 0, 0, 0, 0, 0, 0, 0, 0, 0, 0, 0, 0, 0, 0, 0, 0, 2, 0, 0, 0, 0, 0, 0, 0, 0, 0, 0, 0, 0, 0, 0, 0, 0, 0, 0, 0, 0, 2, 2, 2, 2, 2, 2, 2, 2, 2, 2, 2, 2, 2, 2, 2, 2, 1, -2, -2, 0, 0, 0, 0, 0, 0, 2, 2, 2, 2, 2, 2, 2, 4, -1, 2, 1, 2, 0, 0, 2, 2, 0, 0, -2, 3, 2, 2, 4, 4, 0, -1, -1, -1, -1, -1, -1, -1, -1, -1, -1, -1, -1, -1, -1, -1, -1, -1, -1, -1, -1, -1, -1, -1, -1, -1, -1, -1, -1, -1, -1, -1, -1, -1, -1, -1, -1, -1, -1, -1, -1, -1, -1, -1, -1, -1, -1, -1, -1, -1, -1, -1, -3, -3 };
/* 304:503 */   public static final short[][] TYPE_OF_OPERANDS = { new short[0], new short[0], new short[0], new short[0], new short[0], new short[0], new short[0], new short[0], new short[0], new short[0], new short[0], new short[0], new short[0], new short[0], new short[0], new short[0], { 8 }, { 9 }, { 8 }, { 9 }, { 9 }, { 8 }, { 8 }, { 8 }, { 8 }, { 8 }, new short[0], new short[0], new short[0], new short[0], new short[0], new short[0], new short[0], new short[0], new short[0], new short[0], new short[0], new short[0], new short[0], new short[0], new short[0], new short[0], new short[0], new short[0], new short[0], new short[0], new short[0], new short[0], new short[0], new short[0], new short[0], new short[0], new short[0], new short[0], { 8 }, { 8 }, { 8 }, { 8 }, { 8 }, new short[0], new short[0], new short[0], new short[0], new short[0], new short[0], new short[0], new short[0], new short[0], new short[0], new short[0], new short[0], new short[0], new short[0], new short[0], new short[0], new short[0], new short[0], new short[0], new short[0], new short[0], new short[0], new short[0], new short[0], new short[0], new short[0], new short[0], new short[0], new short[0], new short[0], new short[0], new short[0], new short[0], new short[0], new short[0], new short[0], new short[0], new short[0], new short[0], new short[0], new short[0], new short[0], new short[0], new short[0], new short[0], new short[0], new short[0], new short[0], new short[0], new short[0], new short[0], new short[0], new short[0], new short[0], new short[0], new short[0], new short[0], new short[0], new short[0], new short[0], new short[0], new short[0], new short[0], new short[0], new short[0], new short[0], new short[0], new short[0], new short[0], new short[0], new short[0], new short[0], new short[0], { 8, 8 }, new short[0], new short[0], new short[0], new short[0], new short[0], new short[0], new short[0], new short[0], new short[0], new short[0], new short[0], new short[0], new short[0], new short[0], new short[0], new short[0], new short[0], new short[0], new short[0], new short[0], { 9 }, { 9 }, { 9 }, { 9 }, { 9 }, { 9 }, { 9 }, { 9 }, { 9 }, { 9 }, { 9 }, { 9 }, { 9 }, { 9 }, { 9 }, { 9 }, { 8 }, new short[0], new short[0], new short[0], new short[0], new short[0], new short[0], new short[0], new short[0], { 9 }, { 9 }, { 9 }, { 9 }, { 9 }, { 9 }, { 9 }, { 9, 8, 8 }, new short[0], { 9 }, { 8 }, { 9 }, new short[0], new short[0], { 9 }, { 9 }, new short[0], new short[0], { 8 }, { 9, 8 }, { 9 }, { 9 }, { 10 }, { 10 }, new short[0], new short[0], new short[0], new short[0], new short[0], new short[0], new short[0], new short[0], new short[0], new short[0], new short[0], new short[0], new short[0], new short[0], new short[0], new short[0], new short[0], new short[0], new short[0], new short[0], new short[0], new short[0], new short[0], new short[0], new short[0], new short[0], new short[0], new short[0], new short[0], new short[0], new short[0], new short[0], new short[0], new short[0], new short[0], new short[0], new short[0], new short[0], new short[0], new short[0], new short[0], new short[0], new short[0], new short[0], new short[0], new short[0], new short[0], new short[0], new short[0], new short[0], new short[0], new short[0], new short[0], new short[0] };
/* 305:570 */   public static final String[] OPCODE_NAMES = { "nop", "aconst_null", "iconst_m1", "iconst_0", "iconst_1", "iconst_2", "iconst_3", "iconst_4", "iconst_5", "lconst_0", "lconst_1", "fconst_0", "fconst_1", "fconst_2", "dconst_0", "dconst_1", "bipush", "sipush", "ldc", "ldc_w", "ldc2_w", "iload", "lload", "fload", "dload", "aload", "iload_0", "iload_1", "iload_2", "iload_3", "lload_0", "lload_1", "lload_2", "lload_3", "fload_0", "fload_1", "fload_2", "fload_3", "dload_0", "dload_1", "dload_2", "dload_3", "aload_0", "aload_1", "aload_2", "aload_3", "iaload", "laload", "faload", "daload", "aaload", "baload", "caload", "saload", "istore", "lstore", "fstore", "dstore", "astore", "istore_0", "istore_1", "istore_2", "istore_3", "lstore_0", "lstore_1", "lstore_2", "lstore_3", "fstore_0", "fstore_1", "fstore_2", "fstore_3", "dstore_0", "dstore_1", "dstore_2", "dstore_3", "astore_0", "astore_1", "astore_2", "astore_3", "iastore", "lastore", "fastore", "dastore", "aastore", "bastore", "castore", "sastore", "pop", "pop2", "dup", "dup_x1", "dup_x2", "dup2", "dup2_x1", "dup2_x2", "swap", "iadd", "ladd", "fadd", "dadd", "isub", "lsub", "fsub", "dsub", "imul", "lmul", "fmul", "dmul", "idiv", "ldiv", "fdiv", "ddiv", "irem", "lrem", "frem", "drem", "ineg", "lneg", "fneg", "dneg", "ishl", "lshl", "ishr", "lshr", "iushr", "lushr", "iand", "land", "ior", "lor", "ixor", "lxor", "iinc", "i2l", "i2f", "i2d", "l2i", "l2f", "l2d", "f2i", "f2l", "f2d", "d2i", "d2l", "d2f", "i2b", "i2c", "i2s", "lcmp", "fcmpl", "fcmpg", "dcmpl", "dcmpg", "ifeq", "ifne", "iflt", "ifge", "ifgt", "ifle", "if_icmpeq", "if_icmpne", "if_icmplt", "if_icmpge", "if_icmpgt", "if_icmple", "if_acmpeq", "if_acmpne", "goto", "jsr", "ret", "tableswitch", "lookupswitch", "ireturn", "lreturn", "freturn", "dreturn", "areturn", "return", "getstatic", "putstatic", "getfield", "putfield", "invokevirtual", "invokespecial", "invokestatic", "invokeinterface", "<illegal opcode>", "new", "newarray", "anewarray", "arraylength", "athrow", "checkcast", "instanceof", "monitorenter", "monitorexit", "wide", "multianewarray", "ifnull", "ifnonnull", "goto_w", "jsr_w", "breakpoint", "<illegal opcode>", "<illegal opcode>", "<illegal opcode>", "<illegal opcode>", "<illegal opcode>", "<illegal opcode>", "<illegal opcode>", "<illegal opcode>", "<illegal opcode>", "<illegal opcode>", "<illegal opcode>", "<illegal opcode>", "<illegal opcode>", "<illegal opcode>", "<illegal opcode>", "<illegal opcode>", "<illegal opcode>", "<illegal opcode>", "<illegal opcode>", "<illegal opcode>", "<illegal opcode>", "<illegal opcode>", "<illegal opcode>", "<illegal opcode>", "<illegal opcode>", "<illegal opcode>", "<illegal opcode>", "<illegal opcode>", "<illegal opcode>", "<illegal opcode>", "<illegal opcode>", "<illegal opcode>", "<illegal opcode>", "<illegal opcode>", "<illegal opcode>", "<illegal opcode>", "<illegal opcode>", "<illegal opcode>", "<illegal opcode>", "<illegal opcode>", "<illegal opcode>", "<illegal opcode>", "<illegal opcode>", "<illegal opcode>", "<illegal opcode>", "<illegal opcode>", "<illegal opcode>", "<illegal opcode>", "<illegal opcode>", "<illegal opcode>", "<illegal opcode>", "impdep1", "impdep2" };
/* 306:622 */   public static final int[] CONSUME_STACK = { 0, 0, 0, 0, 0, 0, 0, 0, 0, 0, 0, 0, 0, 0, 0, 0, 0, 0, 0, 0, 0, 0, 0, 0, 0, 0, 0, 0, 0, 0, 0, 0, 0, 0, 0, 0, 0, 0, 0, 0, 0, 0, 0, 0, 0, 0, 2, 2, 2, 2, 2, 2, 2, 2, 1, 2, 1, 2, 1, 1, 1, 1, 1, 2, 2, 2, 2, 1, 1, 1, 1, 2, 2, 2, 2, 1, 1, 1, 1, 3, 4, 3, 4, 3, 3, 3, 3, 1, 2, 1, 2, 3, 2, 3, 4, 2, 2, 4, 2, 4, 2, 4, 2, 4, 2, 4, 2, 4, 2, 4, 2, 4, 2, 4, 2, 4, 1, 2, 1, 2, 2, 3, 2, 3, 2, 3, 2, 4, 2, 4, 2, 4, 0, 1, 1, 1, 2, 2, 2, 1, 1, 1, 2, 2, 2, 1, 1, 1, 4, 2, 2, 4, 4, 1, 1, 1, 1, 1, 1, 2, 2, 2, 2, 2, 2, 2, 2, 0, 0, 0, 1, 1, 1, 2, 1, 2, 1, 0, 0, -2, 1, -2, -2, -2, -2, -2, -1, 0, 1, 1, 1, 1, 1, 1, 1, 1, 0, -2, 1, 1, 0, 0, 0, -1, -1, -1, -1, -1, -1, -1, -1, -1, -1, -1, -1, -1, -1, -1, -1, -1, -1, -1, -1, -1, -1, -1, -1, -1, -1, -1, -1, -1, -1, -1, -1, -1, -1, -1, -1, -1, -1, -1, -1, -1, -1, -1, -1, -1, -1, -1, -1, -1, -1, -1, -2, -2 };
/* 307:676 */   public static final int[] PRODUCE_STACK = { 0, 1, 1, 1, 1, 1, 1, 1, 1, 2, 2, 1, 1, 1, 2, 2, 1, 1, 1, 1, 2, 1, 2, 1, 2, 1, 1, 1, 1, 1, 2, 2, 2, 2, 1, 1, 1, 1, 2, 2, 2, 2, 1, 1, 1, 1, 1, 2, 1, 2, 1, 1, 1, 1, 0, 0, 0, 0, 0, 0, 0, 0, 0, 0, 0, 0, 0, 0, 0, 0, 0, 0, 0, 0, 0, 0, 0, 0, 0, 0, 0, 0, 0, 0, 0, 0, 0, 0, 0, 2, 3, 4, 4, 5, 6, 2, 1, 2, 1, 2, 1, 2, 1, 2, 1, 2, 1, 2, 1, 2, 1, 2, 1, 2, 1, 2, 1, 2, 1, 2, 1, 2, 1, 2, 1, 2, 1, 2, 1, 2, 1, 2, 0, 2, 1, 2, 1, 1, 2, 1, 2, 2, 1, 2, 1, 1, 1, 1, 1, 1, 1, 1, 1, 0, 0, 0, 0, 0, 0, 0, 0, 0, 0, 0, 0, 0, 0, 0, 1, 0, 0, 0, 0, 0, 0, 0, 0, 0, -2, 0, -2, 0, -2, -2, -2, -2, -1, 1, 1, 1, 1, 1, 1, 1, 0, 0, 0, 1, 0, 0, 0, 1, 0, -1, -1, -1, -1, -1, -1, -1, -1, -1, -1, -1, -1, -1, -1, -1, -1, -1, -1, -1, -1, -1, -1, -1, -1, -1, -1, -1, -1, -1, -1, -1, -1, -1, -1, -1, -1, -1, -1, -1, -1, -1, -1, -1, -1, -1, -1, -1, -1, -1, -1, -1, -2, -2 };
/* 308:    */   public static final byte ATTR_UNKNOWN = -1;
/* 309:    */   public static final byte ATTR_SOURCE_FILE = 0;
/* 310:    */   public static final byte ATTR_CONSTANT_VALUE = 1;
/* 311:    */   public static final byte ATTR_CODE = 2;
/* 312:    */   public static final byte ATTR_EXCEPTIONS = 3;
/* 313:    */   public static final byte ATTR_LINE_NUMBER_TABLE = 4;
/* 314:    */   public static final byte ATTR_LOCAL_VARIABLE_TABLE = 5;
/* 315:    */   public static final byte ATTR_INNER_CLASSES = 6;
/* 316:    */   public static final byte ATTR_SYNTHETIC = 7;
/* 317:    */   public static final byte ATTR_DEPRECATED = 8;
/* 318:    */   public static final byte ATTR_PMG = 9;
/* 319:    */   public static final byte ATTR_SIGNATURE = 10;
/* 320:    */   public static final byte ATTR_STACK_MAP = 11;
/* 321:    */   public static final short KNOWN_ATTRIBUTES = 12;
/* 322:745 */   public static final String[] ATTRIBUTE_NAMES = { "SourceFile", "ConstantValue", "Code", "Exceptions", "LineNumberTable", "LocalVariableTable", "InnerClasses", "Synthetic", "Deprecated", "PMGClass", "Signature", "StackMap" };
/* 323:    */   public static final byte ITEM_Bogus = 0;
/* 324:    */   public static final byte ITEM_Integer = 1;
/* 325:    */   public static final byte ITEM_Float = 2;
/* 326:    */   public static final byte ITEM_Double = 3;
/* 327:    */   public static final byte ITEM_Long = 4;
/* 328:    */   public static final byte ITEM_Null = 5;
/* 329:    */   public static final byte ITEM_InitObject = 6;
/* 330:    */   public static final byte ITEM_Object = 7;
/* 331:    */   public static final byte ITEM_NewObject = 8;
/* 332:764 */   public static final String[] ITEM_NAMES = { "Bogus", "Integer", "Float", "Double", "Long", "Null", "InitObject", "Object", "NewObject" };
/* 333:    */ }


/* Location:           G:\ParasiteTrade\Parasite_20150226.jar
 * Qualified Name:     org.apache.bcel.Constants
 * JD-Core Version:    0.7.0.1
 */